imapautofiler/__init__.py
imapautofiler/actions.py
imapautofiler/app.py
imapautofiler/client.py
imapautofiler/config.py
imapautofiler/i18n.py
imapautofiler/lookup.py
imapautofiler/rules.py
imapautofiler/secrets.py
imapautofiler/ui.py
imapautofiler/version.py
imapautofiler/tests/__init__.py
imapautofiler/tests/base.py
imapautofiler/tests/test_actions.py
imapautofiler/tests/test_config.py
imapautofiler/tests/test_lookup.py
imapautofiler/tests/test_maildir.py
imapautofiler/tests/test_rules.py
imapautofiler/tests/test_secrets.py
imapautofiler-2.0.0.dist-info/METADATA
imapautofiler-2.0.0.dist-info/WHEEL
imapautofiler-2.0.0.dist-info/entry_points.txt
imapautofiler-2.0.0.dist-info/licenses/LICENSE
imapautofiler-2.0.0.dist-info/RECORD
